{"resultcode":1,"message":"success","data":{"totalRows":2770,"totalAmount":24847600.0,"donateData":[{"Name":"Nguyễn Kim Ngân","Amount":50000.0,"Description":"Hy vọng các lực lượng tuyến đầu giữ gìn sức khoẻ. Chúc cả nước chống dịch thành công🥰","CreateDate":"2021-06-27T19:47:57"},{"Name":"TRẦN THANH SƠN","Amount":100000.0,"Description":"","CreateDate":"2021-06-27T19:25:57"},{"Name":"Nguyễn Gia Bảo","Amount":10000.0,"Description":"","CreateDate":"2021-06-27T19:23:18"},{"Name":"Hoàng Văn Huy ","Amount":500000.0,"Description":"Việt Nam chiến thắng covid","CreateDate":"2021-06-27T19:21:00"},{"Name":"Lê trọng tài","Amount":20000.0,"Description":"","CreateDate":"2021-06-27T19:19:33"},{"Name":"Thân Thị Mỹ Quyên","Amount":10000.0,"Description":"❤","CreateDate":"2021-06-27T18:42:43"},{"Name":"LÊ THỊ THẢO","Amount":100000.0,"Description":"","CreateDate":"2021-06-27T18:21:09"},{"Name":"Trịnh Văn Toàn","Amount":10000.0,"Description":"","CreateDate":"2021-06-27T18:14:01"},{"Name":"Oliver Woods","Amount":2500000.0,"Description":"My full support for Vietnam's vaccination program!","CreateDate":"2021-06-27T17:21:10"},{"Name":"Hồng Anh","Amount":230500.0,"Description":"","CreateDate":"2021-06-27T17:21:09"},{"Name":"Hương Giang và Bảo Châu","Amount":500000.0,"Description":"","CreateDate":"2021-06-27T16:48:13"},{"Name":"Mai Ngọc Hà","Amount":100000.0,"Description":"VN ơi cố lên","CreateDate":"2021-06-27T16:35:04"},{"Name":"Hai Nguyen","Amount":200000.0,"Description":"Vững vàng qua đại dịch","CreateDate":"2021-06-27T16:27:17"},{"Name":"Phạm Thị Ngọc Duyên","Amount":100000.0,"Description":"","CreateDate":"2021-06-27T16:17:07"},{"Name":"nguyễn diệu linh","Amount":1000000.0,"Description":"mong người dân việt nam trên toàn quốc được tiêm vacxin covid","CreateDate":"2021-06-27T16:15:27"},{"Name":"Anh Sang và Minh Anh","Amount":1000000.0,"Description":"Vì một Việt Nam khoẻ mạnh","CreateDate":"2021-06-27T16:09:23"},{"Name":"Bui Minh Quang","Amount":200000.0,"Description":"VN quyết thắng đại dịch covid 19","CreateDate":"2021-06-27T16:07:47"},{"Name":"Trần Công Bằng","Amount":500000.0,"Description":"Ủng hộ Vaccine để toàn thể người dân cùng nhau vượt qua đại dịch","CreateDate":"2021-06-27T15:57:36"},{"Name":"Thanh Cẩm","Amount":100000.0,"Description":"Việt Nam sẽ chiến thắng nhanh thôi 👍","CreateDate":"2021-06-27T15:16:59"},{"Name":"Phùng Thị Thu Trang","Amount":200000.0,"Description":"","CreateDate":"2021-06-27T15:03:41"},{"Name":"Hoàng Duy Trường","Amount":100000.0,"Description":"","CreateDate":"2021-06-27T14:52:38"},{"Name":"Lê tuyết trinh Láng tròn giá rai bạc liêu","Amount":200000.0,"Description":"Thành công ","CreateDate":"2021-06-27T14:30:53"},{"Name":"Nguyễn  Hoàng  Huyên","Amount":200000.0,"Description":"","CreateDate":"2021-06-27T14:26:03"},{"Name":"PHAM THANH VINH","Amount":50000.0,"Description":"","CreateDate":"2021-06-27T14:22:09"},{"Name":"Cao Thanh Tuyền","Amount":200000.0,"Description":"Mong Tp.hcm sớm hết dịch","CreateDate":"2021-06-27T14:20:54"},{"Name":"Tran Huu Phuc","Amount":300000.0,"Description":"Việt Nam cố lên!!!","CreateDate":"2021-06-27T14:20:38"},{"Name":"Võ Kinh Luân","Amount":500000.0,"Description":"","CreateDate":"2021-06-27T14:15:50"},{"Name":"Trần Thị Lê","Amount":100000.0,"Description":"Việt Nam cố lên","CreateDate":"2021-06-27T14:10:02"},{"Name":"Phạm Thị Hà Thi","Amount":27100.0,"Description":"Việt Nam vô địch ","CreateDate":"2021-06-27T13:53:52"},{"Name":"Tô Thị Tố Trinh","Amount":10000.0,"Description":"Tuy số tiền không nhiều nhưng em hi vọng mình cũng có thể góp phần cùng mọi người đẩy lùi đại dịch","CreateDate":"2021-06-27T13:49:14"},{"Name":"Phạm Sơn Hải","Amount":100000.0,"Description":"","CreateDate":"2021-06-27T13:42:26"},{"Name":"Trần Hoàng Uyên Thục","Amount":200000.0,"Description":"Việt Nam cố lên","CreateDate":"2021-06-27T13:40:56"},{"Name":"NGUYỄN QUANG VINH","Amount":20000.0,"Description":"Cùng chung tay, chúng ta sẽ vượt qua đại dịch 🔥","CreateDate":"2021-06-27T13:38:51"},{"Name":"Bùi Duy Phúc","Amount":500000.0,"Description":"Tất cả người dân Việt Nam hãy ủng hộ cho “Quỹ vắc-xin phòng chống Covid-19”. Vì một Vắc-xin Covid-19.","CreateDate":"2021-06-27T13:29:17"},{"Name":"Phạm Quỳnh Như","Amount":500000.0,"Description":"ung ho quy vac xin phong chong covid","CreateDate":"2021-06-27T13:28:32"},{"Name":" Nguyễn Thái Mỹ Mỹ","Amount":50000.0,"Description":"Mong các bác sĩ tuyến đầu nhiều sức khỏe để chiến thắng bệnh dịch","CreateDate":"2021-06-27T13:20:16"},{"Name":"Vũ Quang Đức","Amount":100000.0,"Description":"","CreateDate":"2021-06-27T13:18:13"},{"Name":"PHAM TRAN NHU QUYNH","Amount":100000.0,"Description":"","CreateDate":"2021-06-27T13:17:21"},{"Name":"Nguyễn thị thu nga","Amount":200000.0,"Description":"Chúc Việt Nam mau khoẻ","CreateDate":"2021-06-27T13:16:32"},{"Name":"Đặng Bá Giáp","Amount":200000.0,"Description":"","CreateDate":"2021-06-27T13:10:16"},{"Name":"TRAN THI NGOC LOAN","Amount":200000.0,"Description":"","CreateDate":"2021-06-27T13:06:07"},{"Name":"Nguyen Thi Lam","Amount":10000.0,"Description":"","CreateDate":"2021-06-27T12:54:55"},{"Name":"BÙI THANH LONG","Amount":200000.0,"Description":"Bùi Thanh Long ủng hộ quỹ vaccine covid","CreateDate":"2021-06-27T12:54:23"},{"Name":"Nguyen Thi Lam","Amount":10000.0,"Description":"","CreateDate":"2021-06-27T12:52:35"},{"Name":"Võ Yến My","Amount":100000.0,"Description":"Chúc cho tất cả bác sĩ, y sĩ tuyến đầu sẽ giữ vững được tinh thần chống dịch nhé. Chúc cho tất cả người dân sẽ được bình an.","CreateDate":"2021-06-27T12:50:00"},{"Name":"Nguyen Thi Lam","Amount":10000.0,"Description":"","CreateDate":"2021-06-27T12:49:13"},{"Name":"Phúc Phạm","Amount":10000.0,"Description":"","CreateDate":"2021-06-27T12:32:14"},{"Name":"Nguyễn Thành Luân","Amount":10000.0,"Description":"Mong Vn Thắng dịch","CreateDate":"2021-06-27T12:29:44"},{"Name":"Phúc Phạm","Amount":5000.0,"Description":"","CreateDate":"2021-06-27T12:27:57"},{"Name":"Nguyen quang vinh","Amount":200000.0,"Description":"","CreateDate":"2021-06-27T12:27:18"},{"Name":"Phúc Phạm","Amount":5000.0,"Description":"","CreateDate":"2021-06-27T12:26:14"},{"Name":"NGUYỄN PHƯƠNG THẢO ","Amount":200000.0,"Description":"","CreateDate":"2021-06-27T12:21:42"},{"Name":"lucke andreany","Amount":100000.0,"Description":"","CreateDate":"2021-06-27T12:17:24"},{"Name":"Doan Thi Nguyet","Amount":500000.0,"Description":"","CreateDate":"2021-06-27T12:16:34"},{"Name":"Nguyen thi thu hang","Amount":10000.0,"Description":"","CreateDate":"2021-06-27T12:15:49"},{"Name":"Quan Chi Mai","Amount":70000.0,"Description":"","CreateDate":"2021-06-27T12:13:55"},{"Name":"Thái Thị An","Amount":50000.0,"Description":"Cầu mong cả nước mau vượt qua đại dịch 🙏","CreateDate":"2021-06-27T12:13:47"},{"Name":"Phúc Phạm","Amount":10000.0,"Description":"","CreateDate":"2021-06-27T12:07:58"},{"Name":"Phúc Phạm","Amount":10000.0,"Description":"","CreateDate":"2021-06-27T12:06:19"},{"Name":"Võ Nguyễn Hoàng Đa","Amount":200000.0,"Description":"Đồng lòng chung tay đẩy lùi covid_19","CreateDate":"2021-06-27T12:04:47"},{"Name":"Nguyen thi thu hang","Amount":10000.0,"Description":"","CreateDate":"2021-06-27T12:04:44"},{"Name":"nguyen the vinh","Amount":20000.0,"Description":"","CreateDate":"2021-06-27T12:04:13"},{"Name":"Phúc Phạm","Amount":10000.0,"Description":"","CreateDate":"2021-06-27T12:03:13"},{"Name":"Lê Thị Bích Hải","Amount":500000.0,"Description":"","CreateDate":"2021-06-27T11:56:28"},{"Name":"Dương Uyên","Amount":300000.0,"Description":"","CreateDate":"2021-06-27T11:49:16"},{"Name":"Lê Thị Hồng Nhung","Amount":20000.0,"Description":"Viet Nam co len","CreateDate":"2021-06-27T11:34:19"},{"Name":"Nguyễn Hữu Nguyên","Amount":500000.0,"Description":"Vì một Việt Nam khỏe mạnh!","CreateDate":"2021-06-27T11:21:01"},{"Name":"Thai Thi Kim Ngan","Amount":2000000.0,"Description":"Việt Nam sẽ làm được ❤️ Stay strong","CreateDate":"2021-06-27T11:06:55"},{"Name":"Phạm Thái Đan Mạnh","Amount":500000.0,"Description":"","CreateDate":"2021-06-27T10:49:10"},{"Name":"Nguyen Thi Lam","Amount":10000.0,"Description":"","CreateDate":"2021-06-27T10:45:33"},{"Name":"Thiên Kim","Amount":10000.0,"Description":"Mong covid19 qua đi để đi học","CreateDate":"2021-06-27T10:39:41"},{"Name":"Cao Thị Nga","Amount":100000.0,"Description":"","CreateDate":"2021-06-27T10:35:44"},{"Name":"Nghiêm Thị Ngọc","Amount":10000.0,"Description":"","CreateDate":"2021-06-27T10:32:12"},{"Name":"Hoàng Anh Đức ","Amount":10000.0,"Description":"Ủng hộ Việt Nam","CreateDate":"2021-06-27T10:24:57"},{"Name":"Dương Hàn Ngọc Vân","Amount":100000.0,"Description":"","CreateDate":"2021-06-27T10:17:34"},{"Name":"NGUYỄN THỊ MỸ TIÊN","Amount":50000.0,"Description":"Viet Nam Co Len","CreateDate":"2021-06-27T10:11:59"},{"Name":"Lê Minh Nguyệt","Amount":100000.0,"Description":"","CreateDate":"2021-06-27T10:11:28"},{"Name":"Ms Tuyền","Amount":20000.0,"Description":"","CreateDate":"2021-06-27T10:10:29"},{"Name":"Hồng","Amount":50000.0,"Description":"","CreateDate":"2021-06-27T09:46:13"},{"Name":"Võ văn Phú ","Amount":100000.0,"Description":"Việt nam chiến thắng đại dịch ","CreateDate":"2021-06-27T09:23:37"},{"Name":"Phùng Bửu Hoàng Lan","Amount":5000.0,"Description":"Hi vọng nhanh chóng hết dịch. ","CreateDate":"2021-06-27T09:22:46"},{"Name":"Nguyễn Ngọc Hải Đường","Amount":100000.0,"Description":"Đóng góp quỹ covid 19","CreateDate":"2021-06-27T09:08:10"},{"Name":"Huỳnh Trúc Linh","Amount":25000.0,"Description":"","CreateDate":"2021-06-27T08:50:46"},{"Name":"Vũ Thu Hạnh","Amount":100000.0,"Description":"Chung tay đẩy lùi dịch bệnh.","CreateDate":"2021-06-27T08:49:29"},{"Name":"Nguyễn Đặng Trà My","Amount":5000000.0,"Description":"Hy vọng quỹ sử dụng đúng mục đích và sớm mang Vắc xin đến với người dân cả nước, đặc biệt là người nghèo , người có thu nhập nhấp, người có nguy cơ lây nhiễm cao","CreateDate":"2021-06-27T08:34:52"},{"Name":"Võ thị hương","Amount":100000.0,"Description":"Chung tay mùa dịch","CreateDate":"2021-06-27T08:25:50"},{"Name":"Phạm Việt Hưng","Amount":100000.0,"Description":"I can do it, We can do it  \nVIET NAM FIGHTING","CreateDate":"2021-06-27T08:06:53"},{"Name":" THANH PHƯƠNG LÊ","Amount":100000.0,"Description":"Chúc các bác sĩ nhiều sức khoẻ","CreateDate":"2021-06-27T08:05:29"},{"Name":"Lưu Văn Cao Trí","Amount":50000.0,"Description":"Mong mọi người cùng chung tay chống dịch. ","CreateDate":"2021-06-27T07:57:56"},{"Name":"Trương Thị Quyên","Amount":100000.0,"Description":"Ủng hộ quỹ Vacxin Covid 19 ","CreateDate":"2021-06-27T07:53:20"},{"Name":"DNTN Phong Phú","Amount":20000.0,"Description":"","CreateDate":"2021-06-27T07:53:15"},{"Name":"Gia Hân","Amount":50000.0,"Description":"","CreateDate":"2021-06-27T07:42:21"},{"Name":"Võ Thị Thanh Thảo","Amount":20000.0,"Description":"Việt Nam cố lên","CreateDate":"2021-06-27T07:24:39"},{"Name":"HỒ QUỐC VIỆT","Amount":100000.0,"Description":"","CreateDate":"2021-06-27T07:09:14"},{"Name":"Trịnh Thị Trang và Nguyễn Hữu Dũng","Amount":200000.0,"Description":"","CreateDate":"2021-06-27T06:57:27"},{"Name":"Nguyễn thị minh trang","Amount":1000000.0,"Description":"","CreateDate":"2021-06-27T06:35:31"},{"Name":"Nguyễn Thị Huyền","Amount":10000.0,"Description":"Ủng hộ Quỹ","CreateDate":"2021-06-27T06:24:01"},{"Name":"Nguyễn đoan ","Amount":50000.0,"Description":"Của ít lòng nhìu vì vn mạnh khoẻ","CreateDate":"2021-06-27T06:11:59"},{"Name":"Trần Thị Trinh","Amount":100000.0,"Description":"Việt Nam cố lên ❤","CreateDate":"2021-06-27T03:34:34"},{"Name":"Nguyễn Huy Dâng","Amount":200000.0,"Description":"Cố lên Việt Nam","CreateDate":"2021-06-27T01:01:45"}]}}